utdf2gmns/__init__.py
utdf2gmns/_utdf2gmns.py
utdf2gmns/engine/__init__.py
utdf2gmns/engine/sigma_x/__init__.py
utdf2gmns/func_lib/__init__.py
utdf2gmns/func_lib/plot_net.py
utdf2gmns/func_lib/gmns/__init__.py
utdf2gmns/func_lib/gmns/geocoding_Links.py
utdf2gmns/func_lib/gmns/geocoding_Nodes.py
utdf2gmns/func_lib/gmns/sigma_x_process_signal_intersection.py
utdf2gmns/func_lib/sumo/SUMO_run_simulation.py
utdf2gmns/func_lib/sumo/__init__.py
utdf2gmns/func_lib/sumo/add_turn_bay.py
utdf2gmns/func_lib/sumo/gmns2sumo.py
utdf2gmns/func_lib/sumo/randomTrips.py
utdf2gmns/func_lib/sumo/read_sumo.py
utdf2gmns/func_lib/sumo/remove_end_route_connection.py
utdf2gmns/func_lib/sumo/remove_u_turn.py
utdf2gmns/func_lib/sumo/signal_intersections.py
utdf2gmns/func_lib/sumo/signal_mapping.py
utdf2gmns/func_lib/sumo/update_sumo_signal_from_utdf.py
utdf2gmns/func_lib/utdf/__init__.py
utdf2gmns/func_lib/utdf/cvt_utdf_lane_df_to_dict.py
utdf2gmns/func_lib/utdf/geocoding_intersection.py
utdf2gmns/func_lib/utdf/read_utdf.py
utdf2gmns/util_lib/__init__.py
utdf2gmns/util_lib/pkg_settings.py
utdf2gmns/util_lib/pkg_utils.py
utdf2gmns-1.1.2.dist-info/licenses/LICENSE
utdf2gmns-1.1.2.dist-info/METADATA
utdf2gmns-1.1.2.dist-info/WHEEL
utdf2gmns-1.1.2.dist-info/top_level.txt
utdf2gmns-1.1.2.dist-info/RECORD
