Metadata-Version: 2.4
Name: utdf2gmns
Version: 1.1.2
Summary: Convert Synchro UTDF data format to other formats, such as GMNS, SUMO, etc...
Home-page: https://github.com/xyluo25/utdf2gmns
Author: Xiangyong Luo
Author-email: Xiangyong Luo <luoxiangyong01@gmail.com>
Maintainer-email: Xiangyong Luo <luoxiangyong01@gmail.com>
Project-URL: Homepage, https://github.com/xyluo25/utdf2gmns
Project-URL: Documentation, https://utdf2gmns.readthedocs.io/en/latest/
Project-URL: Bug Tracker, https://github.com/xyluo25/utdf2gmns/issues
Project-URL: Download, https://www.pepy.tech/projects/utdf2gmns
Keywords: Synchro UTDF,GMNS,SUMO,Conversion,Traffic Microsimulation,Visualization
Classifier: Programming Language :: Python :: 3
Classifier: Programming Language :: Python :: 3.10
Classifier: Programming Language :: Python :: 3.11
Classifier: Programming Language :: Python :: 3.12
Classifier: Operating System :: OS Independent
Requires-Python: >=3.10
License-File: LICENSE
Requires-Dist: pandas>=2.2.3
Requires-Dist: pyufunc>=0.3.7
Provides-Extra: base
Requires-Dist: pandas; extra == "base"
Requires-Dist: pyufunc; extra == "base"
Requires-Dist: pyproj>=3.7.0; extra == "base"
Requires-Dist: geocoder>=1.38.1; extra == "base"
Requires-Dist: geopandas>=1.0.1; extra == "base"
Requires-Dist: geopy>=2.4.1; extra == "base"
Requires-Dist: Shapely>=2.0.7; extra == "base"
Requires-Dist: xlwings>=0.33.9; extra == "base"
Requires-Dist: sumolib; extra == "base"
Requires-Dist: keplergl; extra == "base"
Requires-Dist: matplotlib>=3.10.0; extra == "base"
Provides-Extra: test
Requires-Dist: pytest; extra == "test"
Requires-Dist: coverage; extra == "test"
Requires-Dist: sphinx; extra == "test"
Requires-Dist: myst-parser; extra == "test"
Requires-Dist: sphinx_copybutton; extra == "test"
Provides-Extra: all
Requires-Dist: utdf2gmns[base,test]; extra == "all"
Dynamic: author
Dynamic: home-page
Dynamic: license-file
Dynamic: requires-python
